LICENSE.txt
README.md
pyproject.toml
setup.cfg
setup.py
kizano.egg-info/PKG-INFO
kizano.egg-info/SOURCES.txt
kizano.egg-info/dependency_links.txt
kizano.egg-info/entry_points.txt
kizano.egg-info/requires.txt
kizano.egg-info/top_level.txt
lib/kizano/__init__.py
lib/kizano/utils.py
lib/kizano/logger/__init__.py